sqlee/__init__.py
sqlee/config.py
sqlee/sqlee.py
sqlee/utils/__init__.py
sqlee/utils/backend.py
sqlee/utils/crypto.py
sqlee/utils/exceptions.py
sqlee/utils/gitee.py
sqlee/utils/urlparse.py
sqlee/utils/utils.py
sqlee/utils/django/__init__.py
sqlee/utils/django/handler.py
sqlee/utils/django/models.py
sqlee/utils/django/verify.py
sqlee-2.2.16.dist-info/LICENSE
sqlee-2.2.16.dist-info/METADATA
sqlee-2.2.16.dist-info/WHEEL
sqlee-2.2.16.dist-info/top_level.txt
sqlee-2.2.16.dist-info/RECORD
