Metadata-Version: 2.1
Name: sqlee
Version: 2.2.16
Summary: 基于Gitee API的数据库.
Home-page: https://gitee.com/qu-c/sqlee
Author: Entropy <fu050409@163.com>
Author-email: fu050409@163.com
License: MIT
Project-URL: Bug Tracker, https://gitee.com/qu-c/sqlee/issues
Platform: UNKNOWN
Classifier: Programming Language :: Python :: 3
Classifier: License :: OSI Approved :: MIT License
Classifier: Operating System :: OS Independent
Requires-Python: >=3
License-File: LICENSE
Requires-Dist: requests
Requires-Dist: prompt-toolkit
